unchanged/__init__.py
unchanged/_version.py
unchanged/pytest_plugin.py
unchanged/unchanged.py
unchanged-0.2.dist-info/LICENSE.txt
unchanged-0.2.dist-info/METADATA
unchanged-0.2.dist-info/WHEEL
unchanged-0.2.dist-info/entry_points.txt
unchanged-0.2.dist-info/top_level.txt
unchanged-0.2.dist-info/RECORD
