Metadata-Version: 2.1
Name: unchanged
Version: 0.2
Summary: Simple approval testing.
Author-email: "Nicholas A. Del Grosso" <delgrosso.nick@gmail.com>
Maintainer-email: "Nicholas A. Del Grosso" <delgrosso.nick@gmail.com>
License: MIT License
Classifier: Programming Language :: Python
Requires-Python: >=2.7
License-File: LICENSE.txt
Requires-Dist: pytest
